odoo/addons/edi_storage_oca/README.rst
odoo/addons/edi_storage_oca/__init__.py
odoo/addons/edi_storage_oca/__manifest__.py
odoo/addons/edi_storage_oca/components/__init__.py
odoo/addons/edi_storage_oca/components/base.py
odoo/addons/edi_storage_oca/components/check.py
odoo/addons/edi_storage_oca/components/listener.py
odoo/addons/edi_storage_oca/components/receive.py
odoo/addons/edi_storage_oca/components/send.py
odoo/addons/edi_storage_oca/data/cron.xml
odoo/addons/edi_storage_oca/data/job_channel_data.xml
odoo/addons/edi_storage_oca/data/queue_job_function_data.xml
odoo/addons/edi_storage_oca/demo/edi_backend_demo.xml
odoo/addons/edi_storage_oca/i18n/edi_storage.pot
odoo/addons/edi_storage_oca/i18n/edi_storage_oca.pot
odoo/addons/edi_storage_oca/models/__init__.py
odoo/addons/edi_storage_oca/models/edi_backend.py
odoo/addons/edi_storage_oca/models/edi_exchange_type.py
odoo/addons/edi_storage_oca/readme/CONTRIBUTORS.rst
odoo/addons/edi_storage_oca/readme/DESCRIPTION.rst
odoo/addons/edi_storage_oca/readme/USAGE.rst
odoo/addons/edi_storage_oca/security/ir_model_access.xml
odoo/addons/edi_storage_oca/static/description/icon.png
odoo/addons/edi_storage_oca/static/description/index.html
odoo/addons/edi_storage_oca/tests/__init__.py
odoo/addons/edi_storage_oca/tests/common.py
odoo/addons/edi_storage_oca/tests/test_component_match.py
odoo/addons/edi_storage_oca/tests/test_components_base.py
odoo/addons/edi_storage_oca/tests/test_edi_backend_storage.py
odoo/addons/edi_storage_oca/tests/test_edi_storage_listener.py
odoo/addons/edi_storage_oca/tests/test_exchange_type.py
odoo/addons/edi_storage_oca/views/edi_backend_views.xml
odoo14_addon_edi_storage_oca-14.0.1.8.1.dist-info/METADATA
odoo14_addon_edi_storage_oca-14.0.1.8.1.dist-info/WHEEL
odoo14_addon_edi_storage_oca-14.0.1.8.1.dist-info/top_level.txt
odoo14_addon_edi_storage_oca-14.0.1.8.1.dist-info/RECORD
